README.rst
setup.py
nego/__init__.py
nego/media_type.py
nego/renderer.py
nego.egg-info/PKG-INFO
nego.egg-info/SOURCES.txt
nego.egg-info/dependency_links.txt
nego.egg-info/top_level.txt
tests/__init__.py
tests/test_content_negotiation.py
tests/test_mediatype.py