Metadata-Version: 1.0
Name: nego
Version: 0.1.0
Summary: Content negotiation for every web frameworks.
Home-page: https://github.com/hardtack/nego
Author: Geonu Choi
Author-email: 6566gun@gmail.com
License: MIT LICENSE
Platform: UNKNOWN
